simple_bump/__init__.py
simple_bump/__version__.py
simple_bump/cli/__init__.py
simple_bump/cli/dto.py
simple_bump/cli/main.py
simple_bump/cli/commands/__init__.py
simple_bump/cli/commands/bump.py
simple_bump/cli/commands/config.py
simple_bump/cli/commands/push.py
simple_bump/core/__init__.py
simple_bump/core/errors.py
simple_bump/core/handler.py
simple_bump/core/config/__init__.py
simple_bump/core/config/constants.py
simple_bump/core/config/dto.py
simple_bump/core/config/enums.py
simple_bump/core/operations/__init__.py
simple_bump/core/operations/files.py
simple_bump/core/operations/git.py
simple_bump/core/operations/progress_bar.py
simple_bump-0.4.1.dist-info/LICENSE
simple_bump-0.4.1.dist-info/METADATA
simple_bump-0.4.1.dist-info/WHEEL
simple_bump-0.4.1.dist-info/entry_points.txt
simple_bump-0.4.1.dist-info/top_level.txt
simple_bump-0.4.1.dist-info/RECORD
